{"kind":"symbol","hierarchy":{"paths":[["doc:\/\/IndustrialKit\/documentation\/IndustrialKit","doc:\/\/IndustrialKit\/documentation\/IndustrialKit\/RegistersSelector","doc:\/\/IndustrialKit\/documentation\/IndustrialKit\/RegistersSelector\/View-Implementations"]]},"variants":[{"traits":[{"interfaceLanguage":"swift"}],"paths":["\/documentation\/industrialkit\/registersselector\/searchable(text:tokens:suggestedtokens:ispresented:placement:prompt:token:)-80sd1"]}],"abstract":[{"text":"Inherited from ","type":"text"},{"code":"View.searchable(text:tokens:suggestedTokens:isPresented:placement:prompt:token:)","type":"codeVoice"},{"text":".","type":"text"}],"schemaVersion":{"major":0,"minor":3,"patch":0},"sections":[],"primaryContentSections":[{"declarations":[{"languages":["swift"],"platforms":["macOS"],"tokens":[{"text":"func","kind":"keyword"},{"text":" ","kind":"text"},{"kind":"identifier","text":"searchable"},{"text":"<","kind":"text"},{"text":"C","kind":"genericParameter"},{"text":", ","kind":"text"},{"text":"T","kind":"genericParameter"},{"kind":"text","text":">("},{"kind":"externalParam","text":"text"},{"kind":"text","text":": "},{"kind":"typeIdentifier","text":"Binding","preciseIdentifier":"s:7SwiftUI7BindingV"},{"kind":"text","text":"<"},{"text":"String","kind":"typeIdentifier","preciseIdentifier":"s:SS"},{"kind":"text","text":">, "},{"kind":"externalParam","text":"tokens"},{"text":": ","kind":"text"},{"text":"Binding","kind":"typeIdentifier","preciseIdentifier":"s:7SwiftUI7BindingV"},{"kind":"text","text":"<"},{"kind":"typeIdentifier","text":"C"},{"text":">, ","kind":"text"},{"text":"suggestedTokens","kind":"externalParam"},{"kind":"text","text":": "},{"preciseIdentifier":"s:7SwiftUI7BindingV","kind":"typeIdentifier","text":"Binding"},{"kind":"text","text":"<"},{"kind":"typeIdentifier","text":"C"},{"text":">, ","kind":"text"},{"text":"isPresented","kind":"externalParam"},{"kind":"text","text":": "},{"kind":"typeIdentifier","preciseIdentifier":"s:7SwiftUI7BindingV","text":"Binding"},{"kind":"text","text":"<"},{"preciseIdentifier":"s:Sb","text":"Bool","kind":"typeIdentifier"},{"kind":"text","text":">, "},{"text":"placement","kind":"externalParam"},{"text":": ","kind":"text"},{"text":"SearchFieldPlacement","kind":"typeIdentifier","preciseIdentifier":"s:7SwiftUI20SearchFieldPlacementV"},{"kind":"text","text":" = .automatic, "},{"text":"prompt","kind":"externalParam"},{"kind":"text","text":": "},{"kind":"typeIdentifier","preciseIdentifier":"s:7SwiftUI18LocalizedStringKeyV","text":"LocalizedStringKey"},{"text":", ","kind":"text"},{"kind":"attribute","text":"@"},{"text":"ViewBuilder","preciseIdentifier":"s:7SwiftUI11ViewBuilderV","kind":"attribute"},{"kind":"text","text":" "},{"text":"token","kind":"externalParam"},{"kind":"text","text":": "},{"text":"@escaping","kind":"keyword"},{"kind":"text","text":" ("},{"text":"C","kind":"typeIdentifier"},{"kind":"text","text":"."},{"kind":"typeIdentifier","text":"Element"},{"text":") -> ","kind":"text"},{"text":"T","kind":"typeIdentifier"},{"kind":"text","text":") -> "},{"text":"some","kind":"keyword"},{"text":" ","kind":"text"},{"text":"View","preciseIdentifier":"s:7SwiftUI4ViewP","kind":"typeIdentifier"},{"text":" ","kind":"text"},{"kind":"keyword","text":"where"},{"text":" ","kind":"text"},{"kind":"typeIdentifier","text":"C"},{"text":" : ","kind":"text"},{"kind":"typeIdentifier","text":"RandomAccessCollection","preciseIdentifier":"s:Sk"},{"text":", ","kind":"text"},{"kind":"typeIdentifier","text":"C"},{"kind":"text","text":" : "},{"kind":"typeIdentifier","text":"RangeReplaceableCollection","preciseIdentifier":"s:Sm"},{"text":", ","kind":"text"},{"text":"T","kind":"typeIdentifier"},{"kind":"text","text":" : "},{"preciseIdentifier":"s:7SwiftUI4ViewP","kind":"typeIdentifier","text":"View"},{"kind":"text","text":", "},{"kind":"typeIdentifier","text":"C"},{"kind":"text","text":"."},{"text":"Element","kind":"typeIdentifier"},{"text":" : ","kind":"text"},{"text":"Identifiable","preciseIdentifier":"s:s12IdentifiableP","kind":"typeIdentifier"},{"kind":"text","text":"\n"}]}],"kind":"declarations"}],"metadata":{"fragments":[{"kind":"keyword","text":"func"},{"text":" ","kind":"text"},{"text":"searchable","kind":"identifier"},{"text":"<","kind":"text"},{"kind":"genericParameter","text":"C"},{"kind":"text","text":", "},{"kind":"genericParameter","text":"T"},{"kind":"text","text":">("},{"text":"text","kind":"externalParam"},{"kind":"text","text":": "},{"kind":"typeIdentifier","text":"Binding","preciseIdentifier":"s:7SwiftUI7BindingV"},{"text":"<","kind":"text"},{"text":"String","kind":"typeIdentifier","preciseIdentifier":"s:SS"},{"kind":"text","text":">, "},{"text":"tokens","kind":"externalParam"},{"text":": ","kind":"text"},{"text":"Binding","preciseIdentifier":"s:7SwiftUI7BindingV","kind":"typeIdentifier"},{"kind":"text","text":"<"},{"text":"C","kind":"typeIdentifier"},{"kind":"text","text":">, "},{"kind":"externalParam","text":"suggestedTokens"},{"text":": ","kind":"text"},{"text":"Binding","preciseIdentifier":"s:7SwiftUI7BindingV","kind":"typeIdentifier"},{"text":"<","kind":"text"},{"text":"C","kind":"typeIdentifier"},{"text":">, ","kind":"text"},{"kind":"externalParam","text":"isPresented"},{"text":": ","kind":"text"},{"kind":"typeIdentifier","preciseIdentifier":"s:7SwiftUI7BindingV","text":"Binding"},{"text":"<","kind":"text"},{"kind":"typeIdentifier","text":"Bool","preciseIdentifier":"s:Sb"},{"text":">, ","kind":"text"},{"text":"placement","kind":"externalParam"},{"text":": ","kind":"text"},{"preciseIdentifier":"s:7SwiftUI20SearchFieldPlacementV","text":"SearchFieldPlacement","kind":"typeIdentifier"},{"text":", ","kind":"text"},{"text":"prompt","kind":"externalParam"},{"kind":"text","text":": "},{"text":"LocalizedStringKey","kind":"typeIdentifier","preciseIdentifier":"s:7SwiftUI18LocalizedStringKeyV"},{"kind":"text","text":", "},{"text":"token","kind":"externalParam"},{"kind":"text","text":": ("},{"kind":"typeIdentifier","text":"C"},{"text":".","kind":"text"},{"text":"Element","kind":"typeIdentifier"},{"kind":"text","text":") -> "},{"kind":"typeIdentifier","text":"T"},{"text":") -> ","kind":"text"},{"kind":"keyword","text":"some"},{"kind":"text","text":" "},{"text":"View","kind":"typeIdentifier","preciseIdentifier":"s:7SwiftUI4ViewP"}],"extendedModule":"SwiftUI","modules":[{"name":"IndustrialKit","relatedModules":["SwiftUI"]}],"externalID":"s:7SwiftUI4ViewPAAE10searchable4text6tokens15suggestedTokens11isPresented9placement6prompt5tokenQrAA7BindingVySSG_AMyqd__GAoMySbGAA20SearchFieldPlacementVAA18LocalizedStringKeyVqd_0_7ElementSTQyd__ctSkRd__SmRd__AaBRd_0_s12IdentifiableAVRQr0_lF::SYNTHESIZED::s:13IndustrialKit17RegistersSelectorV","symbolKind":"method","role":"symbol","roleHeading":"Instance Method","platforms":[{"name":"iOS","introducedAt":"17.0","unavailable":false,"beta":false,"deprecated":false},{"beta":false,"introducedAt":"14.0","unavailable":false,"deprecated":false,"name":"macOS"}],"title":"searchable(text:tokens:suggestedTokens:isPresented:placement:prompt:token:)"},"identifier":{"url":"doc:\/\/IndustrialKit\/documentation\/IndustrialKit\/RegistersSelector\/searchable(text:tokens:suggestedTokens:isPresented:placement:prompt:token:)-80sd1","interfaceLanguage":"swift"},"references":{"doc://IndustrialKit/documentation/IndustrialKit/RegistersSelector/searchable(text:tokens:suggestedTokens:isPresented:placement:prompt:token:)-80sd1":{"url":"\/documentation\/industrialkit\/registersselector\/searchable(text:tokens:suggestedtokens:ispresented:placement:prompt:token:)-80sd1","kind":"symbol","identifier":"doc:\/\/IndustrialKit\/documentation\/IndustrialKit\/RegistersSelector\/searchable(text:tokens:suggestedTokens:isPresented:placement:prompt:token:)-80sd1","role":"symbol","fragments":[{"text":"func","kind":"keyword"},{"text":" ","kind":"text"},{"kind":"identifier","text":"searchable"},{"text":"<","kind":"text"},{"text":"C","kind":"genericParameter"},{"kind":"text","text":", "},{"text":"T","kind":"genericParameter"},{"kind":"text","text":">("},{"text":"text","kind":"externalParam"},{"text":": ","kind":"text"},{"preciseIdentifier":"s:7SwiftUI7BindingV","text":"Binding","kind":"typeIdentifier"},{"kind":"text","text":"<"},{"text":"String","kind":"typeIdentifier","preciseIdentifier":"s:SS"},{"text":">, ","kind":"text"},{"text":"tokens","kind":"externalParam"},{"kind":"text","text":": "},{"text":"Binding","kind":"typeIdentifier","preciseIdentifier":"s:7SwiftUI7BindingV"},{"text":"<","kind":"text"},{"text":"C","kind":"typeIdentifier"},{"text":">, ","kind":"text"},{"text":"suggestedTokens","kind":"externalParam"},{"kind":"text","text":": "},{"text":"Binding","kind":"typeIdentifier","preciseIdentifier":"s:7SwiftUI7BindingV"},{"text":"<","kind":"text"},{"kind":"typeIdentifier","text":"C"},{"text":">, ","kind":"text"},{"text":"isPresented","kind":"externalParam"},{"text":": ","kind":"text"},{"preciseIdentifier":"s:7SwiftUI7BindingV","kind":"typeIdentifier","text":"Binding"},{"text":"<","kind":"text"},{"text":"Bool","preciseIdentifier":"s:Sb","kind":"typeIdentifier"},{"kind":"text","text":">, "},{"text":"placement","kind":"externalParam"},{"text":": ","kind":"text"},{"preciseIdentifier":"s:7SwiftUI20SearchFieldPlacementV","text":"SearchFieldPlacement","kind":"typeIdentifier"},{"text":", ","kind":"text"},{"text":"prompt","kind":"externalParam"},{"kind":"text","text":": "},{"text":"LocalizedStringKey","preciseIdentifier":"s:7SwiftUI18LocalizedStringKeyV","kind":"typeIdentifier"},{"kind":"text","text":", "},{"kind":"externalParam","text":"token"},{"text":": (","kind":"text"},{"kind":"typeIdentifier","text":"C"},{"kind":"text","text":"."},{"text":"Element","kind":"typeIdentifier"},{"kind":"text","text":") -> "},{"kind":"typeIdentifier","text":"T"},{"text":") -> ","kind":"text"},{"kind":"keyword","text":"some"},{"text":" ","kind":"text"},{"kind":"typeIdentifier","preciseIdentifier":"s:7SwiftUI4ViewP","text":"View"}],"title":"searchable(text:tokens:suggestedTokens:isPresented:placement:prompt:token:)","abstract":[],"type":"topic"},"doc://IndustrialKit/documentation/IndustrialKit/RegistersSelector":{"kind":"symbol","title":"RegistersSelector","navigatorTitle":[{"text":"RegistersSelector","kind":"identifier"}],"abstract":[],"identifier":"doc:\/\/IndustrialKit\/documentation\/IndustrialKit\/RegistersSelector","type":"topic","role":"symbol","url":"\/documentation\/industrialkit\/registersselector","fragments":[{"text":"struct","kind":"keyword"},{"kind":"text","text":" "},{"text":"RegistersSelector","kind":"identifier"}]},"doc://IndustrialKit/documentation/IndustrialKit/RegistersSelector/View-Implementations":{"kind":"article","title":"View Implementations","abstract":[],"identifier":"doc:\/\/IndustrialKit\/documentation\/IndustrialKit\/RegistersSelector\/View-Implementations","type":"topic","role":"collectionGroup","url":"\/documentation\/industrialkit\/registersselector\/view-implementations"},"doc://IndustrialKit/documentation/IndustrialKit":{"kind":"symbol","type":"topic","url":"\/documentation\/industrialkit","role":"collection","abstract":[],"identifier":"doc:\/\/IndustrialKit\/documentation\/IndustrialKit","title":"IndustrialKit"}}}